py_auth0_jwt_rest-0.1.7.dist-info/METADATA
py_auth0_jwt_rest-0.1.7.dist-info/RECORD
py_auth0_jwt_rest-0.1.7.dist-info/WHEEL
py_auth0_jwt_rest-0.1.7.dist-info/top_level.txt
pyauth0jwtrest/__init__.py
pyauth0jwtrest/apps.py
pyauth0jwtrest/authentication.py
pyauth0jwtrest/settings.py
pyauth0jwtrest/utils.py
