Metadata-Version: 2.1
Name: py-auth0-jwt-rest
Version: 0.1.7
Summary: UNKNOWN
Home-page: https://github.com/hms-dbmi/py-auth0-jwt-rest
Author: HMS DBMI Tech-core
Author-email: dbmi-tech-core@hms.harvard.edu
License: Creative Commons Attribution-Noncommercial-Share Alike license
Platform: UNKNOWN
Requires-Dist: django (>=1.10.0)
Requires-Dist: djangorestframework (>=1.9.0)
Requires-Dist: djangorestframework-jwt (>=1.7.2)
Requires-Dist: cryptography
Requires-Dist: requests
